setup.cfg
setup.py
tests/utils/__init__.py
tests/utils/duplicate_versions.py
tests/utils/mixed_members.py
tests/utils/versioned_members.py
tests/utils/versioned_members_with_number.py
tests/utils/with_number_all_or_none_class.py
tests/utils/with_number_all_or_none_function.py
tests/utils/with_number_inheritance.py
tests/utils/with_number_inheritance_proxy.py
tests/utils/with_number_not_continuous_class.py
tests/utils/with_number_not_continuous_function.py
tests/utils/without_number_all_or_none_class.py
tests/utils/without_number_all_or_none_function.py
tests/utils/without_number_inheritance.py
tests/utils/without_number_inheritance_proxy.py
tests/utils/without_number_not_continuous_class.py
tests/utils/without_number_not_continuous_function.py
versionary/__init__.py
versionary/decorators.py
versionary/exceptions.py
versionary/utils.py
versionary/validators.py
versionary.egg-info/PKG-INFO
versionary.egg-info/SOURCES.txt
versionary.egg-info/dependency_links.txt
versionary.egg-info/requires.txt
versionary.egg-info/top_level.txt